{
    "header_title": "Pasos para realizar un sistema en Spring Boot",
    "header_image": "/data/springboot/spring-boot.png",
    "title": "Estructura de la aplicaci칩n",
    "author": "ing. Abel HZO",
    "content": [
        {
            "subtitle": "游닇 Organizaci칩n de paquetes",
            "text": "Despu칠s de haber hecho los servicios REST, es necesario crear una estructura de paquetes que contendr치n las clases Java que tendr치n como funci칩n realizar una tarea en espec칤fico, como la l칩gica de negocio, acceso a bases de datos, entidades de base de datos, configuraciones de la aplicaci칩n y excepciones personalizadas.<br><br>En la siguiente imagen podemos ver c칩mo se estructurar칤a el proyecto:",
            "image": {
                "src": "/data/springboot/3_organizacion_mvc/resources/image1.png",
                "maxwidth": "400px"
            }
        },
        {
            "text": "De acuerdo a la estructura de la imagen, deber치n quedarnos los paquetes de la siguiente manera:",
            "image": {
                "src": "/data/springboot/3_organizacion_mvc/resources/image2.png",
                "maxwidth": "350px"
            }
        },
        {
            "text": "Ahora solo iremos llenando los paquetes con las clases correspondientes, como en el caso de los DTOs, que ya hemos colocado algunas de las clases DTO que hicimos en el ejercicio anterior; en las siguientes lecciones crearemos las clases para los dem치s paquetes."
        }
    ]
}